recurrentgemma/__init__.py
recurrentgemma/common.py
recurrentgemma/conversion.py
recurrentgemma/conversion_test.py
recurrentgemma/jax/__init__.py
recurrentgemma/jax/array_typing.py
recurrentgemma/jax/complex_lib.py
recurrentgemma/jax/complex_lib_test.py
recurrentgemma/jax/griffin.py
recurrentgemma/jax/griffin_test.py
recurrentgemma/jax/layers.py
recurrentgemma/jax/layers_test.py
recurrentgemma/jax/modules.py
recurrentgemma/jax/modules_test.py
recurrentgemma/jax/pallas.py
recurrentgemma/jax/sampler.py
recurrentgemma/jax/sampler_test.py
recurrentgemma/jax/scan.py
recurrentgemma/jax/utils.py
recurrentgemma/torch/__init__.py
recurrentgemma/torch/array_typing.py
recurrentgemma/torch/griffin.py
recurrentgemma/torch/griffin_test.py
recurrentgemma/torch/layers.py
recurrentgemma/torch/layers_test.py
recurrentgemma/torch/modules.py
recurrentgemma/torch/modules_test.py
recurrentgemma/torch/sampler.py
recurrentgemma/torch/sampler_test.py
recurrentgemma/torch/test_utils.py
recurrentgemma-1.0.0.dist-info/LICENSE
recurrentgemma-1.0.0.dist-info/METADATA
recurrentgemma-1.0.0.dist-info/WHEEL
recurrentgemma-1.0.0.dist-info/RECORD
