Metadata-Version: 2.3
Name: recurrentgemma
Version: 1.0.0
Summary: Open weights large language model (LLM) from Google DeepMind.
License: Apache-2.0
Author: Alex Botev
Author-email: botev@google.com
Requires-Python: >=3,<4
Classifier: License :: OSI Approved :: Apache Software License
Classifier: Programming Language :: Python :: 3
Classifier: Programming Language :: Python :: 3.4
Classifier: Programming Language :: Python :: 3.5
Classifier: Programming Language :: Python :: 3.6
Classifier: Programming Language :: Python :: 3.7
Classifier: Programming Language :: Python :: 3.8
Classifier: Programming Language :: Python :: 3.9
Classifier: Programming Language :: Python :: 3.10
Classifier: Programming Language :: Python :: 3.11
Classifier: Programming Language :: Python :: 3.12
Classifier: Programming Language :: Python :: 3.13
Provides-Extra: full
Provides-Extra: jax
Provides-Extra: test
Provides-Extra: torch
Requires-Dist: absl-py (>=1,<2)
Requires-Dist: einops (>=0,<1)
Requires-Dist: flax (>=0,<1) ; extra == "full" or extra == "jax" or extra == "test"
Requires-Dist: jax (>=0,<1) ; extra == "full" or extra == "jax" or extra == "test"
Requires-Dist: jaxtyping (>=0,<1)
Requires-Dist: numpy (>=2,<3)
Requires-Dist: orbax-checkpoint (>=0,<1) ; extra == "full" or extra == "jax" or extra == "test"
Requires-Dist: pytest (>=8,<9) ; extra == "test"
Requires-Dist: sentencepiece (>=0,<1)
Requires-Dist: torch (>=2,<3) ; extra == "full" or extra == "torch" or extra == "test"
Requires-Dist: typeguard (>=2,<3)
Project-URL: Repository, https://github.com/google-deepmind/recurrentgemma
